setup.cfg
setup.py
cythontest_1/cythontest_1.py
cythontest_1.egg-info/PKG-INFO
cythontest_1.egg-info/SOURCES.txt
cythontest_1.egg-info/dependency_links.txt
cythontest_1.egg-info/not-zip-safe
cythontest_1.egg-info/top_level.txt