Metadata-Version: 2.1
Name: cythontest-1
Version: 1.0.0
Summary: Gaussian and Binomial distributions
Home-page: UNKNOWN
Author-email: xreflake@gmail.com
License: UNKNOWN
Platform: UNKNOWN
